pykd3300/__init__.py
pykd3300/kd3305d.py
pykd3300_tspspi-0.0.1.dist-info/licenses/LICENSE.md
pykd3300_tspspi-0.0.1.dist-info/METADATA
pykd3300_tspspi-0.0.1.dist-info/WHEEL
pykd3300_tspspi-0.0.1.dist-info/top_level.txt
pykd3300_tspspi-0.0.1.dist-info/RECORD
