Metadata-Version: 2.4
Name: pykd3300-tspspi
Version: 0.0.1
Summary: Korad KD3300 interface library (pylabdevs, unofficial)
Author-email: Thomas Spielauer <pypipackages01@tspi.at>
Project-URL: Homepage, https://github.com/tspspi/pykd3300
Classifier: Programming Language :: Python :: 3
Classifier: License :: OSI Approved :: BSD License
Requires-Python: >=3.11
License-File: LICENSE.md
Requires-Dist: pylabdevs-tspspi>=0.0.16
Requires-Dist: pyserial>=3.5
Dynamic: license-file
